pyvcheck/__init__.py
pyvcheck/checker.py
pyvcheck/exceptions.py
pyvcheck/matchers/__init__.py
pyvcheck/matchers/base.py
pyvcheck/matchers/exact.py
pyvcheck/matchers/unary.py
py_vcheck-0.0.2.dist-info/LICENSE
py_vcheck-0.0.2.dist-info/METADATA
py_vcheck-0.0.2.dist-info/WHEEL
py_vcheck-0.0.2.dist-info/top_level.txt
py_vcheck-0.0.2.dist-info/RECORD
